terminusgps_notifications/__init__.py
terminusgps_notifications/admin.py
terminusgps_notifications/apps.py
terminusgps_notifications/constants.py
terminusgps_notifications/models.py
terminusgps_notifications/services.py
terminusgps_notifications/tasks.py
terminusgps_notifications/urls.py
terminusgps_notifications/forms/__init__.py
terminusgps_notifications/forms/customers.py
terminusgps_notifications/forms/notifications.py
terminusgps_notifications/forms/subscriptions.py
terminusgps_notifications/migrations/0001_initial.py
terminusgps_notifications/migrations/0002_alter_wialonnotification_name_and_more.py
terminusgps_notifications/migrations/0003_wialonnotification_resource_name.py
terminusgps_notifications/migrations/__init__.py
terminusgps_notifications/static/terminusgps_notifications/favicon.ico
terminusgps_notifications/static/terminusgps_notifications/css/input.css
terminusgps_notifications/static/terminusgps_notifications/css/output.css
terminusgps_notifications/static/terminusgps_notifications/icon/logo-text.svg
terminusgps_notifications/static/terminusgps_notifications/icon/logo-waypoint.svg
terminusgps_notifications/static/terminusgps_notifications/img/background-dark.png
terminusgps_notifications/static/terminusgps_notifications/img/background-light.png
terminusgps_notifications/static/terminusgps_notifications/js/htmx.min.js
terminusgps_notifications/templates/terminusgps_notifications/contact.html
terminusgps_notifications/templates/terminusgps_notifications/footer.html
terminusgps_notifications/templates/terminusgps_notifications/home.html
terminusgps_notifications/templates/terminusgps_notifications/layout.html
terminusgps_notifications/templates/terminusgps_notifications/logged_out.html
terminusgps_notifications/templates/terminusgps_notifications/login.html
terminusgps_notifications/templates/terminusgps_notifications/navbar.html
terminusgps_notifications/templates/terminusgps_notifications/privacy.html
terminusgps_notifications-1.4.0.dist-info/METADATA
terminusgps_notifications-1.4.0.dist-info/WHEEL
terminusgps_notifications-1.4.0.dist-info/licenses/COPYING
terminusgps_notifications-1.4.0.dist-info/RECORD
