Metadata-Version: 2.4
Name: terminusgps-notifications
Version: 1.4.0
Summary: Terminus GPS Live Notifications platform
Project-URL: Documentation, https://terminusgps.github.io/terminusgps-notifications/
Project-URL: Repository, https://github.com/terminusgps/terminusgps-notifications
License-File: COPYING
Requires-Python: >=3.12
Requires-Dist: django-encrypted-field>=1.0.5
Requires-Dist: django-rq>=3.1
Requires-Dist: django-storages[s3]>=1.14.6
Requires-Dist: django-tasks[rq]>=0.9.0
Requires-Dist: django>=5.2.7
Requires-Dist: python-dateutil>=2.9.0.post0
Requires-Dist: python-terminusgps>=48.1.0
Requires-Dist: redis[hiredis]>=7.0.1
Requires-Dist: terminusgps-payments>=3.0.0
